<?xml version="1.0" encoding="UTF-8"?>
<HSoThueDTu>
	<HSoKhaiThue>
		<TTinChung>
			<TTinDVu>
				<maDVu></maDVu>
				<tenDVu></tenDVu>
				<pbanDVu></pbanDVu>
				<ttinNhaCCapDVu></ttinNhaCCapDVu>
			</TTinDVu>
			<TTinTKhaiThue>
				<TKhaiThue>
					<maTKhai></maTKhai>
					<tenTKhai></tenTKhai>
					<moTaBMau/>
					<pbanTKhaiXML></pbanTKhaiXML>
					<loaiTKhai>C</loaiTKhai>
					<soLan>1</soLan>
					<KyKKhaiThue>
						<kieuKy>D</kieuKy>
						<kyKKhai/>
						<kyKKhaiTuNgay/>
						<kyKKhaiDenNgay/>
						<kyKKhaiTuThang/>
						<kyKKhaiDenThang/>
					</KyKKhaiThue>
					<maCQTNoiNop></maCQTNoiNop>
					<tenCQTNoiNop></tenCQTNoiNop>
					<ngayLapTKhai></ngayLapTKhai>
					<GiaHan>
						<maLyDoGiaHan></maLyDoGiaHan>
						<lyDoGiaHan></lyDoGiaHan>
					</GiaHan>
					<nguoiKy></nguoiKy>
					<ngayKy></ngayKy>
					<nganhNgheKD></nganhNgheKD>
				</TKhaiThue>
				<NNT>
					<mst></mst>
					<tenNNT></tenNNT>
					<dchiNNT></dchiNNT>
					<phuongXa></phuongXa>
					<maHuyenNNT></maHuyenNNT>
					<tenHuyenNNT></tenHuyenNNT>
					<maTinhNNT></maTinhNNT>
					<tenTinhNNT></tenTinhNNT>
					<dthoaiNNT></dthoaiNNT>
					<faxNNT></faxNNT>
					<emailNNT></emailNNT>
				</NNT>
				<DLyThue>
					<mstDLyThue></mstDLyThue>
					<tenDLyThue></tenDLyThue>
					<dchiDLyThue></dchiDLyThue>
					<maHuyenDLyThue></maHuyenDLyThue>
					<tenHuyenDLyThue></tenHuyenDLyThue>
					<maTinhDLyThue></maTinhDLyThue>
					<tenTinhDLyThue></tenTinhDLyThue>
					<dthoaiDLyThue></dthoaiDLyThue>
					<faxDLyThue></faxDLyThue>
					<emailDLyThue></emailDLyThue>
					<soHDongDLyThue></soHDongDLyThue>
					<ngayKyHDDLyThue></ngayKyHDDLyThue>
					<NVienDLy>
						<tenNVienDLyThue></tenNVienDLyThue>
						<cchiHNghe></cchiHNghe>
					</NVienDLy>
				</DLyThue>
			</TTinTKhaiThue>
		</TTinChung>
		<CTieuTKhaiChinh>
			<bctcDaKiemToan>true</bctcDaKiemToan>
			<maYKienKToan></maYKienKToan>
			<tenYKienKToan></tenYKienKToan>
			<ThuyetMinh>
				<ctA_I_tMinh></ctA_I_tMinh>
				<ctA_II_tMinh></ctA_II_tMinh>
				<ctA_III_tMinh></ctA_III_tMinh>
				<ctA_III_1_tMinh></ctA_III_1_tMinh>
				<ctA_III_2_tMinh></ctA_III_2_tMinh>
				<ctA_III_3_tMinh></ctA_III_3_tMinh>
				<ctA_IV_tMinh></ctA_IV_tMinh>
				<ctA_IV_1_tMinh></ctA_IV_1_tMinh>
				<ctA_IV_2_tMinh></ctA_IV_2_tMinh>
				<ctA_V_tMinh></ctA_V_tMinh>
				<ctA_VI_tMinh></ctA_VI_tMinh>
				<ctA_VI_1_tMinh></ctA_VI_1_tMinh>
				<ctA_VI_2_tMinh></ctA_VI_2_tMinh>
				<ctA_VII_moi_tMinh></ctA_VII_moi_tMinh>
				<ctA_VII_1_moi_tMinh></ctA_VII_1_moi_tMinh>
				<ctA_VII_2__moi_tMinh></ctA_VII_2__moi_tMinh>
				<ctA_VII_tMinh></ctA_VII_tMinh>
				<ctA_VII_1_tMinh></ctA_VII_1_tMinh>
				<ctA_VII_2_tMinh></ctA_VII_2_tMinh>
				<ctA_VII_3_tMinh></ctA_VII_3_tMinh>
				<ctA_VIII_tMinh></ctA_VIII_tMinh>
				<ctA_VIII_1_tMinh></ctA_VIII_1_tMinh>
				<ctA_VIII_2_tMinh></ctA_VIII_2_tMinh>
				<ctA_VIII_3_tMinh></ctA_VIII_3_tMinh>
				<ctA_VIII_4_tMinh></ctA_VIII_4_tMinh>
				<ctA_VIII_5_tMinh></ctA_VIII_5_tMinh>
				<ctA_IX_tMinh></ctA_IX_tMinh>
				<ctA_IX_1_tMinh></ctA_IX_1_tMinh>
				<ctA_IX_1_a_tMinh></ctA_IX_1_a_tMinh>
				<ctA_IX_1_b_tMinh></ctA_IX_1_b_tMinh>
				<ctA_IX_2_tMinh></ctA_IX_2_tMinh>
				<ctA_IX_2_a_tMinh></ctA_IX_2_a_tMinh>
				<ctA_IX_2_b_tMinh></ctA_IX_2_b_tMinh>
				<ctA_IX_3_tMinh></ctA_IX_3_tMinh>
				<ctA_IX_3_a_tMinh></ctA_IX_3_a_tMinh>
				<ctA_IX_3_b_tMinh></ctA_IX_3_b_tMinh>
				<ctA_X_tMinh></ctA_X_tMinh>
				<ctA_X_a_tMinh></ctA_X_a_tMinh>
				<ctA_X_b_tMinh></ctA_X_b_tMinh>
				<ctA_XI_tMinh></ctA_XI_tMinh>
				<ctA_XI_1_tMinh></ctA_XI_1_tMinh>
				<ctA_XI_2_tMinh></ctA_XI_2_tMinh>
				<ctA_XI_3_tMinh></ctA_XI_3_tMinh>
				<ctA_XI_4_tMinh></ctA_XI_4_tMinh>
				<ctA_XI_4_1_tMinh></ctA_XI_4_1_tMinh>
				<ctA_XI_5_tMinh></ctA_XI_5_tMinh>
				<tongTsan_tMinh></tongTsan_tMinh>
				<ctB_I_tMinh></ctB_I_tMinh>
				<ctB_II_tMinh></ctB_II_tMinh>
				<ctB_II_1_tMinh></ctB_II_1_tMinh>
				<ctB_II_2_tMinh></ctB_II_2_tMinh>
				<ctB_III_tMinh></ctB_III_tMinh>
				<ctB_IV_tMinh></ctB_IV_tMinh>
				<ctB_V_tMinh></ctB_V_tMinh>
				<ctB_VI_tMinh></ctB_VI_tMinh>
				<ctB_VII_tMinh></ctB_VII_tMinh>
				<ctB_VII_1_tMinh></ctB_VII_1_tMinh>
				<ctB_VII_2_tMinh></ctB_VII_2_tMinh>
				<ctB_VII_3_tMinh></ctB_VII_3_tMinh>
				<ctB_VII_4_tMinh></ctB_VII_4_tMinh>
				<tongNoPTRa_tMinh></tongNoPTRa_tMinh>
				<ctB_VIII_tMinh></ctB_VIII_tMinh>
				<ctB_VIII_1_tMinh></ctB_VIII_1_tMinh>
				<ctB_VIII_1_a_tMinh></ctB_VIII_1_a_tMinh>
				<ctB_VIII_1_b_tMinh></ctB_VIII_1_b_tMinh>
				<ctB_VIII_1_c_tMinh></ctB_VIII_1_c_tMinh>
				<ctB_VIII_1_d_tMinh></ctB_VIII_1_d_tMinh>
				<ctB_VIII_1_e_tMinh></ctB_VIII_1_e_tMinh>
				<ctB_VIII_1_g_tMinh></ctB_VIII_1_g_tMinh>
				<ctB_VIII_2_tMinh></ctB_VIII_2_tMinh>
				<ctB_VIII_3_tMinh></ctB_VIII_3_tMinh>
				<ctB_VIII_4_tMinh></ctB_VIII_4_tMinh>
				<ctB_VIII_5_tMinh></ctB_VIII_5_tMinh>
				<ctB_IX_tMinh></ctB_IX_tMinh>
				<tongNoVon_tMinh></tongNoVon_tMinh>
				<blanhVon_tMinh></blanhVon_tMinh>
				<ckGDHoiDoai_tMinh></ckGDHoiDoai_tMinh>
				<ckMuaNTe_tMinh></ckMuaNTe_tMinh>
				<ckBanNTe_tMinh></ckBanNTe_tMinh>
				<ckGDHoanDoi_tMinh></ckGDHoanDoi_tMinh>
				<ckGDTuongLai_tMinh></ckGDTuongLai_tMinh>
				<ckCVayKHuyNgang_tMinh></ckCVayKHuyNgang_tMinh>
				<cketNVu_tMinh></cketNVu_tMinh>
				<blanhKhac_tMinh></blanhKhac_tMinh>
				<cketKhac_tMinh></cketKhac_tMinh>
			</ThuyetMinh>
			<SoNamNay>
				<ctA_I_nNay></ctA_I_nNay>
				<ctA_II_nNay></ctA_II_nNay>
				<ctA_III_nNay></ctA_III_nNay>
				<ctA_III_1_nNay></ctA_III_1_nNay>
				<ctA_III_2_nNay></ctA_III_2_nNay>
				<ctA_III_3_nNay></ctA_III_3_nNay>
				<ctA_IV_nNay></ctA_IV_nNay>
				<ctA_IV_1_nNay></ctA_IV_1_nNay>
				<ctA_IV_2_nNay></ctA_IV_2_nNay>
				<ctA_V_nNay></ctA_V_nNay>
				<ctA_VI_nNay></ctA_VI_nNay>
				<ctA_VI_1_nNay></ctA_VI_1_nNay>
				<ctA_VI_2_nNay></ctA_VI_2_nNay>
				<ctA_VII_moi_nNay></ctA_VII_moi_nNay>
				<ctA_VII_1_moi_nNay></ctA_VII_1_moi_nNay>
				<ctA_VII_2__moi_nNay></ctA_VII_2__moi_nNay>
				<ctA_VII_nNay></ctA_VII_nNay>
				<ctA_VII_1_nNay></ctA_VII_1_nNay>
				<ctA_VII_2_nNay></ctA_VII_2_nNay>
				<ctA_VII_3_nNay></ctA_VII_3_nNay>
				<ctA_VIII_nNay></ctA_VIII_nNay>
				<ctA_VIII_1_nNay></ctA_VIII_1_nNay>
				<ctA_VIII_2_nNay></ctA_VIII_2_nNay>
				<ctA_VIII_3_nNay></ctA_VIII_3_nNay>
				<ctA_VIII_4_nNay></ctA_VIII_4_nNay>
				<ctA_VIII_5_nNay></ctA_VIII_5_nNay>
				<ctA_IX_nNay></ctA_IX_nNay>
				<ctA_IX_1_nNay></ctA_IX_1_nNay>
				<ctA_IX_1_a_nNay></ctA_IX_1_a_nNay>
				<ctA_IX_1_b_nNay></ctA_IX_1_b_nNay>
				<ctA_IX_2_nNay></ctA_IX_2_nNay>
				<ctA_IX_2_a_nNay></ctA_IX_2_a_nNay>
				<ctA_IX_2_b_nNay></ctA_IX_2_b_nNay>
				<ctA_IX_3_nNay></ctA_IX_3_nNay>
				<ctA_IX_3_a_nNay></ctA_IX_3_a_nNay>
				<ctA_IX_3_b_nNay></ctA_IX_3_b_nNay>
				<ctA_X_nNay></ctA_X_nNay>
				<ctA_X_a_nNay></ctA_X_a_nNay>
				<ctA_X_b_nNay></ctA_X_b_nNay>
				<ctA_XI_nNay></ctA_XI_nNay>
				<ctA_XI_1_nNay></ctA_XI_1_nNay>
				<ctA_XI_2_nNay></ctA_XI_2_nNay>
				<ctA_XI_3_nNay></ctA_XI_3_nNay>
				<ctA_XI_4_nNay></ctA_XI_4_nNay>
				<ctA_XI_4_1_nNay></ctA_XI_4_1_nNay>
				<ctA_XI_5_nNay></ctA_XI_5_nNay>
				<tongTsan_nNay></tongTsan_nNay>
				<ctB_I_nNay></ctB_I_nNay>
				<ctB_II_nNay></ctB_II_nNay>
				<ctB_II_1_nNay></ctB_II_1_nNay>
				<ctB_II_2_nNay></ctB_II_2_nNay>
				<ctB_III_nNay></ctB_III_nNay>
				<ctB_IV_nNay></ctB_IV_nNay>
				<ctB_V_nNay></ctB_V_nNay>
				<ctB_VI_nNay></ctB_VI_nNay>
				<ctB_VII_nNay></ctB_VII_nNay>
				<ctB_VII_1_nNay></ctB_VII_1_nNay>
				<ctB_VII_2_nNay></ctB_VII_2_nNay>
				<ctB_VII_3_nNay></ctB_VII_3_nNay>
				<ctB_VII_4_nNay></ctB_VII_4_nNay>
				<tongNoPTRa_nNay></tongNoPTRa_nNay>
				<ctB_VIII_nNay></ctB_VIII_nNay>
				<ctB_VIII_1_nNay></ctB_VIII_1_nNay>
				<ctB_VIII_1_a_nNay></ctB_VIII_1_a_nNay>
				<ctB_VIII_1_b_nNay></ctB_VIII_1_b_nNay>
				<ctB_VIII_1_c_nNay></ctB_VIII_1_c_nNay>
				<ctB_VIII_1_d_nNay></ctB_VIII_1_d_nNay>
				<ctB_VIII_1_e_nNay></ctB_VIII_1_e_nNay>
				<ctB_VIII_1_g_nNay></ctB_VIII_1_g_nNay>
				<ctB_VIII_2_nNay></ctB_VIII_2_nNay>
				<ctB_VIII_3_nNay></ctB_VIII_3_nNay>
				<ctB_VIII_4_nNay></ctB_VIII_4_nNay>
				<ctB_VIII_5_nNay></ctB_VIII_5_nNay>
				<ctB_IX_nNay></ctB_IX_nNay>
				<tongNoVon_nNay></tongNoVon_nNay>
				<blanhVon_nNay></blanhVon_nNay>
				<ckGDHoiDoai_nNay></ckGDHoiDoai_nNay>
				<ckMuaNTe_nNay></ckMuaNTe_nNay>
				<ckBanNTe_nNay></ckBanNTe_nNay>
				<ckGDHoanDoi_nNay></ckGDHoanDoi_nNay>
				<ckGDTuongLai_nNay></ckGDTuongLai_nNay>
				<ckCVayKHuyNgang_nNay></ckCVayKHuyNgang_nNay>
				<cketNVu_nNay></cketNVu_nNay>
				<blanhKhac_nNay></blanhKhac_nNay>
				<cketKhac_nNay></cketKhac_nNay>
			</SoNamNay>
			<SoNamNgoai>
				<ctA_I_nNgoai></ctA_I_nNgoai>
				<ctA_II_nNgoai></ctA_II_nNgoai>
				<ctA_III_nNgoai></ctA_III_nNgoai>
				<ctA_III_1_nNgoai></ctA_III_1_nNgoai>
				<ctA_III_2_nNgoai></ctA_III_2_nNgoai>
				<ctA_III_3_nNgoai></ctA_III_3_nNgoai>
				<ctA_IV_nNgoai></ctA_IV_nNgoai>
				<ctA_IV_1_nNgoai></ctA_IV_1_nNgoai>
				<ctA_IV_2_nNgoai></ctA_IV_2_nNgoai>
				<ctA_V_nNgoai></ctA_V_nNgoai>
				<ctA_VI_nNgoai></ctA_VI_nNgoai>
				<ctA_VI_1_nNgoai></ctA_VI_1_nNgoai>
				<ctA_VI_2_nNgoai></ctA_VI_2_nNgoai>
				<ctA_VII_moi_nNgoai></ctA_VII_moi_nNgoai>
				<ctA_VII_1_moi_nNgoai></ctA_VII_1_moi_nNgoai>
				<ctA_VII_2__moi_nNgoai></ctA_VII_2__moi_nNgoai>
				<ctA_VII_nNgoai></ctA_VII_nNgoai>
				<ctA_VII_1_nNgoai></ctA_VII_1_nNgoai>
				<ctA_VII_2_nNgoai></ctA_VII_2_nNgoai>
				<ctA_VII_3_nNgoai></ctA_VII_3_nNgoai>
				<ctA_VIII_nNgoai></ctA_VIII_nNgoai>
				<ctA_VIII_1_nNgoai></ctA_VIII_1_nNgoai>
				<ctA_VIII_2_nNgoai></ctA_VIII_2_nNgoai>
				<ctA_VIII_3_nNgoai></ctA_VIII_3_nNgoai>
				<ctA_VIII_4_nNgoai></ctA_VIII_4_nNgoai>
				<ctA_VIII_5_nNgoai></ctA_VIII_5_nNgoai>
				<ctA_IX_nNgoai></ctA_IX_nNgoai>
				<ctA_IX_1_nNgoai></ctA_IX_1_nNgoai>
				<ctA_IX_1_a_nNgoai></ctA_IX_1_a_nNgoai>
				<ctA_IX_1_b_nNgoai></ctA_IX_1_b_nNgoai>
				<ctA_IX_2_nNgoai></ctA_IX_2_nNgoai>
				<ctA_IX_2_a_nNgoai></ctA_IX_2_a_nNgoai>
				<ctA_IX_2_b_nNgoai></ctA_IX_2_b_nNgoai>
				<ctA_IX_3_nNgoai></ctA_IX_3_nNgoai>
				<ctA_IX_3_a_nNgoai></ctA_IX_3_a_nNgoai>
				<ctA_IX_3_b_nNgoai></ctA_IX_3_b_nNgoai>
				<ctA_X_nNgoai></ctA_X_nNgoai>
				<ctA_X_a_nNgoai></ctA_X_a_nNgoai>
				<ctA_X_b_nNgoai></ctA_X_b_nNgoai>
				<ctA_XI_nNgoai></ctA_XI_nNgoai>
				<ctA_XI_1_nNgoai></ctA_XI_1_nNgoai>
				<ctA_XI_2_nNgoai></ctA_XI_2_nNgoai>
				<ctA_XI_3_nNgoai></ctA_XI_3_nNgoai>
				<ctA_XI_4_nNgoai></ctA_XI_4_nNgoai>
				<ctA_XI_4_1_nNgoai></ctA_XI_4_1_nNgoai>
				<ctA_XI_5_nNgoai></ctA_XI_5_nNgoai>
				<tongTsan_nNgoai></tongTsan_nNgoai>
				<ctB_I_nNgoai></ctB_I_nNgoai>
				<ctB_II_nNgoai></ctB_II_nNgoai>
				<ctB_II_1_nNgoai></ctB_II_1_nNgoai>
				<ctB_II_2_nNgoai></ctB_II_2_nNgoai>
				<ctB_III_nNgoai></ctB_III_nNgoai>
				<ctB_IV_nNgoai></ctB_IV_nNgoai>
				<ctB_V_nNgoai></ctB_V_nNgoai>
				<ctB_VI_nNgoai></ctB_VI_nNgoai>
				<ctB_VII_nNgoai></ctB_VII_nNgoai>
				<ctB_VII_1_nNgoai></ctB_VII_1_nNgoai>
				<ctB_VII_2_nNgoai></ctB_VII_2_nNgoai>
				<ctB_VII_3_nNgoai></ctB_VII_3_nNgoai>
				<ctB_VII_4_nNgoai></ctB_VII_4_nNgoai>
				<tongNoPTRa_nNgoai></tongNoPTRa_nNgoai>
				<ctB_VIII_nNgoai></ctB_VIII_nNgoai>
				<ctB_VIII_1_nNgoai></ctB_VIII_1_nNgoai>
				<ctB_VIII_1_a_nNgoai></ctB_VIII_1_a_nNgoai>
				<ctB_VIII_1_b_nNgoai></ctB_VIII_1_b_nNgoai>
				<ctB_VIII_1_c_nNgoai></ctB_VIII_1_c_nNgoai>
				<ctB_VIII_1_d_nNgoai></ctB_VIII_1_d_nNgoai>
				<ctB_VIII_1_e_nNgoai></ctB_VIII_1_e_nNgoai>
				<ctB_VIII_1_g_nNgoai></ctB_VIII_1_g_nNgoai>
				<ctB_VIII_2_nNgoai></ctB_VIII_2_nNgoai>
				<ctB_VIII_3_nNgoai></ctB_VIII_3_nNgoai>
				<ctB_VIII_4_nNgoai></ctB_VIII_4_nNgoai>
				<ctB_VIII_5_nNgoai></ctB_VIII_5_nNgoai>
				<ctB_IX_nNgoai></ctB_IX_nNgoai>
				<tongNoVon_nNgoai></tongNoVon_nNgoai>
				<blanhVon_nNgoai></blanhVon_nNgoai>
				<ckGDHoiDoai_nNgoai></ckGDHoiDoai_nNgoai>
				<ckMuaNTe_nNgoai></ckMuaNTe_nNgoai>
				<ckBanNTe_nNgoai></ckBanNTe_nNgoai>
				<ckGDHoanDoi_nNgoai></ckGDHoanDoi_nNgoai>
				<ckGDTuongLai_nNgoai></ckGDTuongLai_nNgoai>
				<ckCVayKHuyNgang_nNgoai></ckCVayKHuyNgang_nNgoai>
				<cketNVu_nNgoai></cketNVu_nNgoai>
				<blanhKhac_nNgoai></blanhKhac_nNgoai>
				<cketKhac_nNgoai></cketKhac_nNgoai>
			</SoNamNgoai>
			<PhanKy>
				<nguoiLapBieu></nguoiLapBieu>
				<keToanTruong></keToanTruong>
				<ngayLap></ngayLap>
				<giamDoc></giamDoc>
			</PhanKy>
		</CTieuTKhaiChinh>
		<PLuc>
		</PLuc>
	</HSoKhaiThue>
</HSoThueDTu>
