<Sections Version="432">
  <Section Dynamic="0" MaxRows="0">
    <Items>
		<Item Value="0###217###21701###2170101###Phường Dữu Lâu" />
		<Item Value="0###217###21701###2170103###Phường Vân Cơ" />
		<Item Value="0###217###21701###2170105###Phường Nông Trang" />
		<Item Value="0###217###21701###2170107###Phường Gia Cẩm" />
		<Item Value="0###217###21701###2170109###Phường Thọ Sơn" />
		<Item Value="0###217###21701###2170111###Phường Thanh Miếu" />
		<Item Value="0###217###21701###2170113###Phường Bạch Hạc" />
		<Item Value="0###217###21701###2170115###Phường Vân Phú" />
		<Item Value="0###217###21701###2170117###Xã Phượng Lâu" />
		<Item Value="0###217###21701###2170119###Xã Thụy Vân" />
		<Item Value="0###217###21701###2170121###Phường Minh Phương" />
		<Item Value="0###217###21701###2170123###Xã Sông Lô" />
		<Item Value="0###217###21701###2170125###Phường Tân Dân" />
		<Item Value="0###217###21701###2170127###Phường Minh Nông" />
		<Item Value="0###217###21701###2170129###Phường Tiên Cát" />
		<Item Value="0###217###21701###2170131###Phường Bến Gót" />
		<Item Value="0###217###21701###2170133###Xã Trưng Vương" />
		<Item Value="0###217###21701###2170135###Xã Tân Đức (hết hiệu lực)" />
		<Item Value="0###217###21701###2170137###Xã Kim Đức" />
		<Item Value="0###217###21701###2170139###Xã Hy Cương" />
		<Item Value="0###217###21701###2170141###Xã Chu Hoá" />
		<Item Value="0###217###21701###2170143###Xã Thanh Đình" />
		<Item Value="0###217###21701###2170145###Xã Hùng Lô" />
		<Item Value="0###217###21703###2170301###Phường Trường Thịnh (hết hiệu lực)" />
		<Item Value="0###217###21703###2170303###Phường Phong Châu" />
		<Item Value="0###217###21703###2170305###Phường âu Cơ" />
		<Item Value="0###217###21703###2170307###Xã Hà Lộc" />
		<Item Value="0###217###21703###2170309###Xã Văn Lung" />
		<Item Value="0###217###21703###2170311###Xã Thanh Minh" />
		<Item Value="0###217###21703###2170313###Xã Hà Thạch" />
		<Item Value="0###217###21703###2170315###Phường Hùng Vương" />
		<Item Value="0###217###21703###2170317###Xã Phú Hộ" />
		<Item Value="0###217###21703###2170319###Phường Thanh Vinh" />
		<Item Value="0###217###21705###2170501###Xã Đông Khê (hết hiệu lực)" />
		<Item Value="0###217###21705###2170503###Xã Nghinh Xuyên (hết hiệu lực)" />
		<Item Value="0###217###21705###2170505###Xã Bằng Luân" />
		<Item Value="0###217###21705###2170507###Xã Vân Du" />
		<Item Value="0###217###21705###2170509###Xã Phương Trung (hết hiệu lực)" />
		<Item Value="0###217###21705###2170511###Xã Minh Lương" />
		<Item Value="0###217###21705###2170513###Xã Bằng Doãn" />
		<Item Value="0###217###21705###2170515###Xã Chí Đám" />
		<Item Value="0###217###21705###2170517###Xã Phúc Lai" />
		<Item Value="0###217###21705###2170519###Xã Ngọc Quan" />
		<Item Value="0###217###21705###2170521###Xã Sóc Đăng" />
		<Item Value="0###217###21705###2170523###Xã Phú Thứ (hết hiệu lực)" />
		<Item Value="0###217###21705###2170525###Xã Tây Cốc" />
		<Item Value="0###217###21705###2170527###Xã Hùng Long" />
		<Item Value="0###217###21705###2170529###Xã Vụ Quang" />
		<Item Value="0###217###21705###2170531###Xã Vân Đồn" />
		<Item Value="0###217###21705###2170533###Xã Minh Tiến" />
		<Item Value="0###217###21705###2170535###Xã Chân Mộng" />
		<Item Value="0###217###21705###2170537###Thị trấn Đoan Hùng" />
		<Item Value="0###217###21705###2170539###Xã Hữu Đô (hết hiệu lực)" />
		<Item Value="0###217###21705###2170541###Xã Minh Phú" />
		<Item Value="0###217###21705###2170543###Xã Hùng Quan (hết hiệu lực)" />
		<Item Value="0###217###21705###2170545###Xã Quế Lâm (hết hiệu lực)" />
		<Item Value="0###217###21705###2170547###Xã Phong Phú (hết hiệu lực)" />
		<Item Value="0###217###21705###2170549###Xã Đại Nghĩa (hết hiệu lực)" />
		<Item Value="0###217###21705###2170551###Xã Yên Kiện" />
		<Item Value="0###217###21705###2170553###Xã Tiêu Sơn" />
		<Item Value="0###217###21705###2170555###Xã Ca Đình" />
		<Item Value="0###217###21705###2170557###Xã Hùng Xuyên" />
		<Item Value="0###217###21705###2170559###Xã Hợp Nhất" />
		<Item Value="0###217###21705###2170561###Xã Phú Lâm" />  
		<Item Value="0###217###21707###2170701###Thị trấn Hạ Hoà" />
		<Item Value="0###217###21707###2170703###Xã Đại Phạm" />
		<Item Value="0###217###21707###2170705###Xã Đan Hà (hết hiệu lực)" />
		<Item Value="0###217###21707###2170707###Xã Hà Lương" />
		<Item Value="0###217###21707###2170709###Xã Lệnh Khanh (hết hiệu lực)" />
		<Item Value="0###217###21707###2170711###Xã Liên Phương (hết hiệu lực)" />
		<Item Value="0###217###21707###2170713###Xã Đan Thượng" />
		<Item Value="0###217###21707###2170715###Xã Lâm Lợi (hết hiệu lực)" />
		<Item Value="0###217###21707###2170717###Xã Phương Viên" />
		<Item Value="0###217###21707###2170719###Xã Gia Điền" />
		<Item Value="0###217###21707###2170721###Xã Quân Khê (hết hiệu lực)" />
		<Item Value="0###217###21707###2170723###Xã Y Sơn (hết hiệu lực)" />
		<Item Value="0###217###21707###2170725###Xã Hương Xạ" />
		<Item Value="0###217###21707###2170727###Xã Xuân áng" />
		<Item Value="0###217###21707###2170729###Xã Yên Kỳ" />
		<Item Value="0###217###21707###2170731###Xã Lang Sơn" />
		<Item Value="0###217###21707###2170733###Xã Bằng Giã" />
		<Item Value="0###217###21707###2170735###Xã Vô Tranh" />
		<Item Value="0###217###21707###2170737###Xã Văn Lang" />
		<Item Value="0###217###21707###2170739###Xã Chính Công (hết hiệu lực)" />
		<Item Value="0###217###21707###2170741###Xã Vĩnh Chân" />
		<Item Value="0###217###21707###2170743###Xã Mai Tùng (hết hiệu lực)" />
		<Item Value="0###217###21707###2170745###Xã Vụ Cầu (hết hiệu lực)" />
		<Item Value="0###217###21707###2170747###Xã Hiền Lương" />
		<Item Value="0###217###21707###2170749###Xã Chuế Lưu (hết hiệu lực)" />
		<Item Value="0###217###21707###2170751###Xã Minh Côi" />
		<Item Value="0###217###21707###2170753###Xã Yên Luật" />
		<Item Value="0###217###21707###2170755###Xã Hậu Bổng (hết hiệu lực)" />
		<Item Value="0###217###21707###2170757###Xã Phụ Khánh (hết hiệu lực)" />
		<Item Value="0###217###21707###2170759###Xã Động Lâm (hết hiệu lực)" />
		<Item Value="0###217###21707###2170761###Xã ấm Hạ" />
		<Item Value="0###217###21707###2170763###Xã Cáo Điền (hết hiệu lực)" />
		<Item Value="0###217###21707###2170765###Xã Minh Hạc" />
		<Item Value="0###217###21707###2170767###Xã Tứ Hiệp" />
		<Item Value="0###217###21709###2170901###Xã Mạn Lạn" />
		<Item Value="0###217###21709###2170903###Xã Thanh Xá (hết hiệu lực)" />
		<Item Value="0###217###21709###2170905###Xã Chí Tiên" />
		<Item Value="0###217###21709###2170907###Xã Hoàng Cương" />
		<Item Value="0###217###21709###2170909###Xã Sơn Cương" />
		<Item Value="0###217###21709###2170911###Xã Thanh Hà" />
		<Item Value="0###217###21709###2170913###Xã Đỗ Sơn" />
		<Item Value="0###217###21709###2170915###Xã Đỗ Xuyên" />
		<Item Value="0###217###21709###2170917###Xã Lương Lỗ" />
		<Item Value="0###217###21709###2170919###Xã Khải Xuân" />
		<Item Value="0###217###21709###2170921###Xã Đông Lĩnh" />
		<Item Value="0###217###21709###2170923###Xã Đại An" />
		<Item Value="0###217###21709###2170925###Xã Hanh Cù" />
		<Item Value="0###217###21709###2170927###Xã Đồng Xuân" />
		<Item Value="0###217###21709###2170929###Xã Năng Yên (hết hiệu lực)" />
		<Item Value="0###217###21709###2170931###Xã Yển Khê (hết hiệu lực)" />
		<Item Value="0###217###21709###2170933###Xã Quảng Nạp (hết hiệu lực)" />
		<Item Value="0###217###21709###2170935###Xã Vũ Yển (hết hiệu lực)" />
		<Item Value="0###217###21709###2170937###Xã Võ Lao" />
		<Item Value="0###217###21709###2170939###Xã Đông Thành" />
		<Item Value="0###217###21709###2170941###Xã Thanh Vân (hết hiệu lực)" />
		<Item Value="0###217###21709###2170943###Xã Yên Nội (hết hiệu lực)" />
		<Item Value="0###217###21709###2170945###Thị trấn Thanh Ba" />
		<Item Value="0###217###21709###2170947###Xã Thái Ninh (hết hiệu lực)" />
		<Item Value="0###217###21709###2170949###Xã Ninh Dân" />
		<Item Value="0###217###21709###2170951###Xã Phương Lĩnh (hết hiệu lực)" />
		<Item Value="0###217###21709###2170955###Xã Quảng Yên" />
		<Item Value="0###217###21709###2170953###Xã Vân Lĩnh" />
		<Item Value="0###217###21711###2171101###Xã Phú Mỹ" />
		<Item Value="0###217###21711###2171103###Xã Liên Hoa" />
		<Item Value="0###217###21711###2171105###Xã Trạm Thản" />
		<Item Value="0###217###21711###2171107###Xã Tiên Phú" />
		<Item Value="0###217###21711###2171109###Xã Hạ Giáp" />
		<Item Value="0###217###21711###2171111###Xã Bảo Thanh" />
		<Item Value="0###217###21711###2171113###Xã Gia Thanh" />
		<Item Value="0###217###21711###2171115###Xã Tiên Du" />
		<Item Value="0###217###21711###2171117###Xã Bình Bộ (hết hiệu lực)" />
		<Item Value="0###217###21711###2171119###Xã An Đạo" />
		<Item Value="0###217###21711###2171123###Xã Vĩnh Phú (hết hiệu lực)" />
		<Item Value="0###217###21711###2171127###Xã Trị Quận" />
		<Item Value="0###217###21711###2171129###Xã Tử Đà (hết hiệu lực)" />
		<Item Value="0###217###21711###2171131###Thị trấn Phong Châu" />
		<Item Value="0###217###21711###2171133###Xã Trung Giáp" />
		<Item Value="0###217###21711###2171135###Xã Phú Lộc" />
		<Item Value="0###217###21711###2171137###Xã Phú Nham" />
		<Item Value="0###217###21711###2171139###Xã Phù Ninh" />
		<Item Value="0###217###21711###2171141###Xã Lệ Mỹ" />
		<Item Value="0###217###21711###2171143###Xã Bình Phú" />
		<Item Value="0###217###21713###2171301###Xã Tuy Lộc" />
		<Item Value="0###217###21713###2171303###Xã Ngô Xá" />
		<Item Value="0###217###21713###2171305###Xã Phương Xá (hết hiệu lực)" />
		<Item Value="0###217###21713###2171307###Xã Đồng Cam (hết hiệu lực)" />
		<Item Value="0###217###21713###2171309###Xã Thụy Liễu" />
		<Item Value="0###217###21713###2171311###Xã Phùng Xá (hết hiệu lực)" />
		<Item Value="0###217###21713###2171313###Xã Sai Nga (hết hiệu lực)" />
		<Item Value="0###217###21713###2171315###Xã Tùng Khê" />
		<Item Value="0###217###21713###2171317###Xã Văn Bán" />
		<Item Value="0###217###21713###2171319###Xã Thanh Nga (hết hiệu lực)" />
		<Item Value="0###217###21713###2171321###Xã Phú Khê" />
		<Item Value="0###217###21713###2171323###Xã Sơn Tình" />
		<Item Value="0###217###21713###2171325###Xã Yên Tập" />
		<Item Value="0###217###21713###2171327###Xã Tạ Xá" />
		<Item Value="0###217###21713###2171329###Xã Phú Lạc" />
		<Item Value="0###217###21713###2171331###Xã Tình Cương (hết hiệu lực)" />
		<Item Value="0###217###21713###2171333###Xã Văn Khúc" />
		<Item Value="0###217###21713###2171335###Xã Yên Dưỡng" />
		<Item Value="0###217###21713###2171337###Xã Điêu Lương" />
		<Item Value="0###217###21713###2171339###Xã Đồng Lương" />
		<Item Value="0###217###21713###2171341###Xã Tiên Lương" />
		<Item Value="0###217###21713###2171343###Xã Cấp Dẫn" />
		<Item Value="0###217###21713###2171345###Xã Hiền Đa (hết hiệu lực)" />
		<Item Value="0###217###21713###2171347###Thị trấn Sông Thao (hết hiệu lực)" />
		<Item Value="0###217###21713###2171349###Xã Phượng Vĩ" />
		<Item Value="0###217###21713###2171351###Xã Sơn Nga (hết hiệu lực)" />
		<Item Value="0###217###21713###2171353###Xã Tam Sơn" />
		<Item Value="0###217###21713###2171355###Xã Xương Thịnh" />
		<Item Value="0###217###21713###2171357###Xã Hương Lung" />
		<Item Value="0###217###21713###2171359###Xã Chương Xá" />
		<Item Value="0###217###21713###2171361###Xã Cát Trù (hết hiệu lực)" />
		<Item Value="0###217###21713###2171363###Xã Minh Tân" />
		<Item Value="0###217###21713###2171365###Thị trấn Cẩm Khê" />
		<Item Value="0###217###21713###2171367###Xã Hùng Vệt" />
		<Item Value="0###217###21715###2171501###Xã Mỹ Lung" />
		<Item Value="0###217###21715###2171503###Xã Mỹ Lương" />
		<Item Value="0###217###21715###2171505###Xã Lương Sơn" />
		<Item Value="0###217###21715###2171507###Xã Xuân An" />
		<Item Value="0###217###21715###2171509###Xã Trung Sơn" />
		<Item Value="0###217###21715###2171511###Xã Hưng Long" />
		<Item Value="0###217###21715###2171513###Xã Đồng Lạc" />
		<Item Value="0###217###21715###2171515###Xã Thượng Long" />
		<Item Value="0###217###21715###2171517###Xã Đồng Thịnh" />
		<Item Value="0###217###21715###2171519###Xã Minh Hòa" />
		<Item Value="0###217###21715###2171521###Xã Ngọc Lập" />
		<Item Value="0###217###21715###2171523###Xã Ngọc Đồng" />
		<Item Value="0###217###21715###2171525###Xã Xuân Thủy" />
		<Item Value="0###217###21715###2171527###Thị trấn Yên Lập" />
		<Item Value="0###217###21715###2171529###Xã Xuân Viên" />
		<Item Value="0###217###21715###2171531###Xã Nga Hoàng" />
		<Item Value="0###217###21715###2171533###Xã Phúc Khánh" />
		<Item Value="0###217###21717###2171701###Thị trấn Hưng Hoá" />
		<Item Value="0###217###21717###2171703###Xã Hiền Quan" />
		<Item Value="0###217###21717###2171705###Xã Hương Nha (hết hiệu lực)" />
		<Item Value="0###217###21717###2171707###Xã Thanh Uyên" />
		<Item Value="0###217###21717###2171709###Xã Văn Lương (hết hiệu lực)" />
		<Item Value="0###217###21717###2171711###Xã Hùng Đô (hết hiệu lực)" />
		<Item Value="0###217###21717###2171713###Xã Tam Cường (hết hiệu lực)" />
		<Item Value="0###217###21717###2171715###Xã Cổ Tiết (hết hiệu lực)" />
		<Item Value="0###217###21717###2171717###Xã Quang Húc" />
		<Item Value="0###217###21717###2171719###Xã Hương Nộn" />
		<Item Value="0###217###21717###2171721###Xã Thọ Văn" />
		<Item Value="0###217###21717###2171723###Xã Dậu Dương (hết hiệu lực)" />
		<Item Value="0###217###21717###2171725###Xã Thượng Nông (hết hiệu lực)" />
		<Item Value="0###217###21717###2171727###Xã Tứ Mỹ (hết hiệu lực)" />
		<Item Value="0###217###21717###2171729###Xã Dị Nậu" />
		<Item Value="0###217###21717###2171731###Xã Vực Trường (hết hiệu lực)" />
		<Item Value="0###217###21717###2171733###Xã Xuân Quang (hết hiệu lực)" />
		<Item Value="0###217###21717###2171735###Xã Phương Thịnh (hết hiệu lực)" />
		<Item Value="0###217###21717###2171737###Xã Tề Lễ" />
		<Item Value="0###217###21717###2171739###Xã Hồng Đà (hết hiệu lực)" />
		<Item Value="0###217###21717###2171741###Xã Dân Quyền" />
		<Item Value="0###217###21717###2171743###Xã Lam Sơn" />
		<Item Value="0###217###21717###2171745###Xã Vạn Xuân" />
		<Item Value="0###217###21717###2171747###Xã Bắc Sơn" />
		<Item Value="0###217###21719###2171901###Thị trấn Thanh Sơn" />
		<Item Value="0###217###21719###2171913###Xã Sơn Hùng" />
		<Item Value="0###217###21719###2171917###Xã Địch Quả" />
		<Item Value="0###217###21719###2171919###Xã Giáp Lai" />
		<Item Value="0###217###21719###2171921###Xã Thục Luyện" />
		<Item Value="0###217###21719###2171923###Xã Võ Miếu" />
		<Item Value="0###217###21719###2171931###Xã Tất Thắng" />
		<Item Value="0###217###21719###2171935###Xã Cự Đồng" />
		<Item Value="0###217###21719###2171943###Xã Hương Cần" />
		<Item Value="0###217###21719###2171945###Xã Đông Cửu" />
		<Item Value="0###217###21719###2171947###Xã Tân Lập" />
		<Item Value="0###217###21719###2171949###Xã Yên Lãng" />
		<Item Value="0###217###21719###2171951###Xã Thượng Cửu" />
		<Item Value="0###217###21719###2171953###Xã Lương Nha" />
		<Item Value="0###217###21719###2171955###Xã Yên Sơn" />
		<Item Value="0###217###21719###2171961###Xã Tân Minh" />
		<Item Value="0###217###21719###2171965###Xã Thạch Khoán" />
		<Item Value="0###217###21719###2171967###Xã Cự Thắng" />
		<Item Value="0###217###21719###2171969###Xã Văn Miếu" />
		<Item Value="0###217###21719###2171971###Xã Thắng Sơn" />
		<Item Value="0###217###21719###2171973###Xã Khả Cửu" />
		<Item Value="0###217###21719###2171975###Xã Yên Lương" />
		<Item Value="0###217###21719###2171977###Xã Tinh Nhuệ" />
		<Item Value="0###217###21720###2172001###Xã Tân Sơn" />
		<Item Value="0###217###21720###2172003###Xã Xuân Đài" />
		<Item Value="0###217###21720###2172005###Xã Văn Luông" />
		<Item Value="0###217###21720###2172007###Xã Xuân Sơn" />
		<Item Value="0###217###21720###2172009###Xã Long Cốc" />
		<Item Value="0###217###21720###2172011###Xã Kim Thượng" />
		<Item Value="0###217###21720###2172013###Xã Tam Thanh" />
		<Item Value="0###217###21720###2172015###Xã Vinh Tiền" />
		<Item Value="0###217###21720###2172017###Xã Đồng Sơn" />
		<Item Value="0###217###21720###2172019###Xã Minh Đài" />
		<Item Value="0###217###21720###2172021###Xã Tân Phú" />
		<Item Value="0###217###21720###2172025###Xã Thu Cúc" />
		<Item Value="0###217###21720###2172027###Xã Thạch Kiệt" />
		<Item Value="0###217###21720###2172029###Xã Thu Ngạc" />
		<Item Value="0###217###21720###2172031###Xã Kiệt Sơn" />
		<Item Value="0###217###21720###2172033###Xã Lai Đồng" />
		<Item Value="0###217###21720###2172035###Xã Mỹ Thuận" />
		<Item Value="0###217###21721###2172101###Xã Bản Nguyên" />
		<Item Value="0###217###21721###2172103###Xã Tứ Xã" />
		<Item Value="0###217###21721###2172105###Thị trấn Lâm Thao" />
		<Item Value="0###217###21721###2172107###Thị trấn Hùng Sơn" />
		<Item Value="0###217###21721###2172109###Xã Xuân Lũng" />
		<Item Value="0###217###21721###2172117###Xã Sơn Vi" />
		<Item Value="0###217###21721###2172119###Xã Sơn Dương (hết hiệu lực)" />
		<Item Value="0###217###21721###2172121###Xã Cao Xá" />
		<Item Value="0###217###21721###2172123###Xã Vĩnh Lại" />
		<Item Value="0###217###21721###2172125###Xã Thạch Sơn" />
		<Item Value="0###217###21721###2172127###Xã Tiên Kiên" />
		<Item Value="0###217###21721###2172129###Xã Xuân Huy" />
		<Item Value="0###217###21721###2172131###Xã Hợp Hải (hết hiệu lực)" />
		<Item Value="0###217###21721###2172133###Xã Kinh Kệ (hết hiệu lực)" />
		<Item Value="0###217###21721###2172135###Xã Phùng Nguyên" />
		<Item Value="0###217###21723###2172301###Xã Đào Xá" />
		<Item Value="0###217###21723###2172303###Xã Xuân Lộc" />
		<Item Value="0###217###21723###2172305###Thị trấn Thanh Thuỷ" />
		<Item Value="0###217###21723###2172307###Xã Sơn Thủy" />
		<Item Value="0###217###21723###2172309###Xã Bảo Yên" />
		<Item Value="0###217###21723###2172311###Xã Đồng Luận (hết hiệu lực)" />
		<Item Value="0###217###21723###2172313###Xã Hoàng Xá" />
		<Item Value="0###217###21723###2172315###Xã Trung Thịnh (hết hiệu lực)" />
		<Item Value="0###217###21723###2172317###Xã Phượng Mao (hết hiệu lực)" />
		<Item Value="0###217###21723###2172319###Xã Tu Vũ" />
		<Item Value="0###217###21723###2172321###Xã Thạch Đồng" />
		<Item Value="0###217###21723###2172323###Xã Yến Mao (hết hiệu lực)" />
		<Item Value="0###217###21723###2172325###Xã Tân Phương" />
		<Item Value="0###217###21723###2172327###Xã Đoan Hạ" />
		<Item Value="0###217###21723###2172329###Xã Trung Nghĩa (hết hiệu lực)" />
		<Item Value="0###217###21723###2172331###Xã Đồng Trung" />
    </Items>
  </Section>
</Sections>
